<DOMSymbolItem xmlns:xsi="http://www.w3.org/2001/XMLSchema-instance" xmlns="http://ns.adobe.com/xfl/2008/" name="sequence/bbb22" itemID="5273651f-0000036a" sourceFlashFilepath="../../../../julietacastanos/Desktop/Module 01 Time Value Of Money 20June2014_2.fla" sourceLibraryItemHRef="sequence/bbb22" sourceLastModified="1383294239" lastModified="1383294239" sourceItemID="00000000-ffffffff">
  <timeline>
    <DOMTimeline name="bbb22">
      <layers>
        <DOMLayer name="Layer 1" color="#4FFF4F" current="true" isSelected="true">
          <frames>
            <DOMFrame index="0" keyMode="9728">
              <elements>
                <DOMGroup selected="true">
                  <members>
                    <DOMShape selected="true">
                      <fills>
                        <FillStyle index="1">
                          <SolidColor color="#FFFFFF"/>
                        </FillStyle>
                      </fills>
                      <edges>
                        <Edge fillStyle1="1" edges="!718 102S2[736 121 737 156!737 156[736 188 720 215!720 215[698 246 663 250!663 250[633 252 614 236!614 236[595 219 593 189!593 189|621 183!621 183[624 205 635 217!635 217[647 226 663 225!663 225[681 223 695 206!695 206[708 188 708 161
!708 161[708 136 695 123!695 123[682 109 662 111!662 111[649 111 638 119!638 119[628 127 622 138!622 138|597 137!597 137|619 10!619 10|727 0!727 0|727 29!727 29|640 36!640 36|628 103!628 103[647 85 670 84!670 84[698 81 718 102!524 107
[504 150 493 195!493 195[484 226 482 264!482 264|454 267!454 267[455 237 464 195!464 195[474 153 493 113!493 113[510 74 531 46!531 46|423 56!423 56|423 26!423 26|566 14!566 14|566 37!566 37[545 64 524 107!255 101[255 74 273 54!273 54
[291 33 321 31!321 31[349 29 367 46!367 46[385 63 386 90!386 90[385 107 377 121!377 121[369 134 353 143!353 143[373 148 384 163!384 163[395 179 395 202!395 202[394 234 374 257!374 257[354 281 322 285!322 285[287 288 267 269!267 269[245
 249 245 216!245 216[245 192 257 175!257 175[268 157 290 149!290 149[271 143 263 132!263 132[255 119 255 101!294 69[284 82 284 98!284 98[284 115 294 126!294 126[304 135 322 134!322 134[337 132 347 121!347 121[357 108 357 93!357 93[357
 75 347 66!347 66[336 54 321 56!321 56[304 57 294 69!367 205[367 183 354 171!354 171[340 157 321 159!321 159[300 161 288 177!288 177[274 192 274 213!274 213[274 226 281 238!281 238[287 249 297 255!297 255[308 261 322 259!322 259[341 257
 354 243!354 243[367 227 367 205!85 52|85 304!85 304|57 307!57 307|57 110!57 110[46 121 30 134!30 134[13 146 0 152!0 152|0 123!0 123[23 108 41 90!41 90[59 70 67 54!67 54|85 52!205 258|205 292!205 292|173 296!173 296|173 261!173 261|205
 258"/>
                      </edges>
                    </DOMShape>
                  </members>
                </DOMGroup>
              </elements>
            </DOMFrame>
          </frames>
        </DOMLayer>
      </layers>
    </DOMTimeline>
  </timeline>
</DOMSymbolItem>